pydantic_mcp_client/__init__.py
pydantic_mcp_client/client.py
pydantic_mcp_client-0.1.2.dist-info/licenses/LICENSE
pydantic_mcp_client-0.1.2.dist-info/WHEEL
pydantic_mcp_client-0.1.2.dist-info/METADATA
pydantic_mcp_client-0.1.2.dist-info/RECORD
